money2number/__init__.py
money2number/m2n.py
money2number-0.7.dist-info/METADATA
money2number-0.7.dist-info/WHEEL
money2number-0.7.dist-info/top_level.txt
money2number-0.7.dist-info/RECORD
