Metadata-Version: 2.1
Name: money2number
Version: 0.7
Summary: Convert a single money related term in a sentence in any format to float.
Home-page: https://github.com/sarsiz/money_to_number
Author: Sarsiz Chauhan
Author-email: sarsiz97@gmail.com
License: UNKNOWN
Platform: UNKNOWN
